buddy_config/__init__.py
buddy_config/config.py
buddy_config-0.1.7.dist-info/LICENSE
buddy_config-0.1.7.dist-info/METADATA
buddy_config-0.1.7.dist-info/WHEEL
buddy_config-0.1.7.dist-info/top_level.txt
buddy_config-0.1.7.dist-info/RECORD
