Metadata-Version: 2.1
Name: buddy-config
Version: 0.1.7
Summary: Lazy environment variable configuration of declarative style.
Home-page: https://github.com/I159/buddy_config
Author: Ilya 'I159' Pekelny
Author-email: pekelny@gmail.com
License: MIT
Platform: UNKNOWN
Classifier: Development Status :: 2 - Pre-Alpha
Classifier: Intended Audience :: Developers
Classifier: License :: OSI Approved :: GNU General Public License v3 (GPLv3)
Classifier: Programming Language :: Python :: 3
Classifier: Programming Language :: Python :: 3.7
